[
    {
        "id": 25,
        "name": "Level 25",
        "grid": {
            "width": 7,
            "height": 7
        },
        "items": [
            {
                "x": 0,
                "y": 2,
                "type": "CELL_TYPES.RECEIVER"
            },
            {
                "x": 2,
                "y": 5,
                "type": "CELL_TYPES.RECEIVER"
            },
            {
                "x": 4,
                "y": 1,
                "type": "CELL_TYPES.RECEIVER"
            },
            {
                "x": 3,
                "y": 3,
                "type": "CELL_TYPES.MIRROR_TRIANGLE",
                "rotation": 2,
                "locked": true,
                "fixedRotation": true
            }
        ],
        "emitters": [
            {
                "x": 1,
                "y": 7,
                "direction": "DIRECTIONS.UP"
            },
            {
                "x": 5,
                "y": 7,
                "direction": "DIRECTIONS.UP"
            }
        ],
        "inventory": {
            "mirror1": 2,
            "mirror2": 0
        }
    },
    {
        "id": 26,
        "name": "Level 26",
        "grid": {
            "width": 7,
            "height": 7
        },
        "items": [
            {
                "x": 0,
                "y": 2,
                "type": "CELL_TYPES.RECEIVER"
            },
            {
                "x": 0,
                "y": 4,
                "type": "CELL_TYPES.RECEIVER"
            },
            {
                "x": 6,
                "y": 2,
                "type": "CELL_TYPES.RECEIVER"
            },
            {
                "x": 6,
                "y": 4,
                "type": "CELL_TYPES.RECEIVER"
            },
            {
                "x": 3,
                "y": 3,
                "type": "CELL_TYPES.WALL"
            },
            {
                "x": 1,
                "y": 6,
                "type": "CELL_TYPES.MIRROR_TRIANGLE",
                "rotation": 3,
                "locked": true,
                "fixedRotation": true
            },
            {
                "x": 5,
                "y": 0,
                "type": "CELL_TYPES.MIRROR_TRIANGLE",
                "rotation": 1,
                "locked": true,
                "fixedRotation": true
            }
        ],
        "emitters": [
            {
                "x": -1,
                "y": 3,
                "direction": "DIRECTIONS.RIGHT"
            },
            {
                "x": 7,
                "y": 3,
                "direction": "DIRECTIONS.LEFT"
            }
        ],
        "inventory": {
            "mirror1": 2,
            "mirror2": 0
        }
    },
    {
        "id": 27,
        "name": "Level 27",
        "grid": {
            "width": 7,
            "height": 7
        },
        "items": [
            {
                "x": 1,
                "y": 2,
                "type": "CELL_TYPES.RECEIVER"
            },
            {
                "x": 2,
                "y": 6,
                "type": "CELL_TYPES.RECEIVER"
            },
            {
                "x": 5,
                "y": 3,
                "type": "CELL_TYPES.RECEIVER"
            },
            {
                "x": 5,
                "y": 6,
                "type": "CELL_TYPES.MIRROR_TRIANGLE",
                "rotation": 0,
                "locked": true,
                "fixedRotation": true
            }
        ],
        "emitters": [
            {
                "x": -1,
                "y": 1,
                "direction": "DIRECTIONS.RIGHT"
            }
        ],
        "inventory": {
            "mirror1": 2,
            "mirror2": 0
        }
    },
    {
        "id": 28,
        "name": "Level 28",
        "grid": {
            "width": 7,
            "height": 7
        },
        "items": [
            {
                "x": 2,
                "y": 6,
                "type": "CELL_TYPES.RECEIVER"
            },
            {
                "x": 4,
                "y": 0,
                "type": "CELL_TYPES.RECEIVER"
            },
            {
                "x": 3,
                "y": 0,
                "type": "CELL_TYPES.MIRROR_TRIANGLE",
                "rotation": 1,
                "locked": true,
                "fixedRotation": false
            },
            {
                "x": 3,
                "y": 6,
                "type": "CELL_TYPES.MIRROR_TRIANGLE",
                "rotation": 3,
                "locked": true,
                "fixedRotation": false
            }
        ],
        "emitters": [
            {
                "x": -1,
                "y": 3,
                "direction": "DIRECTIONS.RIGHT"
            },
            {
                "x": 7,
                "y": 3,
                "direction": "DIRECTIONS.LEFT"
            }
        ],
        "inventory": {
            "mirror1": 0,
            "mirror2": 0
        }
    },
    {
        "id": 29,
        "name": "Level 29",
        "grid": {
            "width": 6,
            "height": 6
        },
        "items": [
            {
                "x": 0,
                "y": 5,
                "type": "CELL_TYPES.RECEIVER"
            },
            {
                "x": 1,
                "y": 1,
                "type": "CELL_TYPES.WALL"
            },
            {
                "x": 2,
                "y": 1,
                "type": "CELL_TYPES.WALL"
            },
            {
                "x": 3,
                "y": 1,
                "type": "CELL_TYPES.WALL"
            },
            {
                "x": 4,
                "y": 1,
                "type": "CELL_TYPES.WALL"
            },
            {
                "x": 1,
                "y": 3,
                "type": "CELL_TYPES.WALL"
            },
            {
                "x": 2,
                "y": 3,
                "type": "CELL_TYPES.WALL"
            },
            {
                "x": 3,
                "y": 3,
                "type": "CELL_TYPES.WALL"
            },
            {
                "x": 4,
                "y": 3,
                "type": "CELL_TYPES.WALL"
            },
            {
                "x": 0,
                "y": 2,
                "type": "CELL_TYPES.MIRROR_TRIANGLE",
                "rotation": 0,
                "locked": true,
                "fixedRotation": false
            },
            {
                "x": 5,
                "y": 5,
                "type": "CELL_TYPES.MIRROR_TRIANGLE",
                "rotation": 0,
                "locked": true,
                "fixedRotation": true
            }
        ],
        "emitters": [
            {
                "x": 0,
                "y": -1,
                "direction": "DIRECTIONS.DOWN"
            }
        ],
        "inventory": {
            "mirror1": 0,
            "mirror2": 1
        }
    },
    {
        "id": 30,
        "name": "Level 30",
        "grid": {
            "width": 7,
            "height": 7
        },
        "items": [
            {
                "x": 3,
                "y": 3,
                "type": "CELL_TYPES.EMITTER",
                "direction": "DIRECTIONS.RIGHT"
            },
            {
                "x": 1,
                "y": 0,
                "type": "CELL_TYPES.RECEIVER"
            },
            {
                "x": 1,
                "y": 2,
                "type": "CELL_TYPES.RECEIVER"
            },
            {
                "x": 1,
                "y": 5,
                "type": "CELL_TYPES.RECEIVER"
            },
            {
                "x": 6,
                "y": 3,
                "type": "CELL_TYPES.RECEIVER"
            },
            {
                "x": 1,
                "y": 1,
                "type": "CELL_TYPES.WALL"
            },
            {
                "x": 2,
                "y": 1,
                "type": "CELL_TYPES.WALL"
            },
            {
                "x": 3,
                "y": 1,
                "type": "CELL_TYPES.WALL"
            },
            {
                "x": 3,
                "y": 2,
                "type": "CELL_TYPES.WALL"
            },
            {
                "x": 1,
                "y": 4,
                "type": "CELL_TYPES.WALL"
            },
            {
                "x": 2,
                "y": 4,
                "type": "CELL_TYPES.WALL"
            },
            {
                "x": 3,
                "y": 4,
                "type": "CELL_TYPES.WALL"
            },
            {
                "x": 4,
                "y": 4,
                "type": "CELL_TYPES.WALL"
            },
            {
                "x": 4,
                "y": 5,
                "type": "CELL_TYPES.WALL"
            },
            {
                "x": 5,
                "y": 5,
                "type": "CELL_TYPES.WALL"
            },
            {
                "x": 0,
                "y": 6,
                "type": "CELL_TYPES.WALL"
            },
            {
                "x": 1,
                "y": 6,
                "type": "CELL_TYPES.WALL"
            },
            {
                "x": 2,
                "y": 6,
                "type": "CELL_TYPES.WALL"
            },
            {
                "x": 0,
                "y": 3,
                "type": "CELL_TYPES.MIRROR_TRIANGLE",
                "rotation": 0,
                "locked": true,
                "fixedRotation": false
            },
            {
                "x": 3,
                "y": 5,
                "type": "CELL_TYPES.MIRROR_TRIANGLE",
                "rotation": 0,
                "locked": true,
                "fixedRotation": false
            },
            {
                "x": 6,
                "y": 0,
                "type": "CELL_TYPES.MIRROR_TRIANGLE",
                "rotation": 1,
                "locked": true,
                "fixedRotation": true
            }
        ],
        "emitters": [],
        "inventory": {
            "mirror1": 3,
            "mirror2": 2
        }
    },
    {
        "id": 31,
        "name": "Level 31",
        "grid": {
            "width": 7,
            "height": 3
        },
        "items": [
            {
                "x": 6,
                "y": 0,
                "type": "CELL_TYPES.RECEIVER"
            },
            {
                "x": 0,
                "y": 1,
                "type": "CELL_TYPES.MIRROR_TRIANGLE",
                "rotation": 0,
                "locked": true,
                "fixedRotation": false
            },
            {
                "x": 2,
                "y": 0,
                "type": "CELL_TYPES.MIRROR_TRIANGLE",
                "rotation": 0,
                "locked": true,
                "fixedRotation": false
            },
            {
                "x": 2,
                "y": 2,
                "type": "CELL_TYPES.MIRROR_TRIANGLE",
                "rotation": 0,
                "locked": true,
                "fixedRotation": false
            },
            {
                "x": 4,
                "y": 0,
                "type": "CELL_TYPES.MIRROR_TRIANGLE",
                "rotation": 0,
                "locked": true,
                "fixedRotation": false
            },
            {
                "x": 4,
                "y": 2,
                "type": "CELL_TYPES.MIRROR_TRIANGLE",
                "rotation": 0,
                "locked": true,
                "fixedRotation": false
            },
            {
                "x": 6,
                "y": 2,
                "type": "CELL_TYPES.MIRROR_TRIANGLE",
                "rotation": 0,
                "locked": true,
                "fixedRotation": false
            }
        ],
        "emitters": [
            {
                "x": -1,
                "y": 1,
                "direction": "DIRECTIONS.RIGHT"
            }
        ],
        "inventory": {
            "mirror1": 0,
            "mirror2": 0
        }
    },
    {
        "id": 32,
        "name": "Level 32",
        "grid": {
            "width": 7,
            "height": 5
        },
        "items": [
            {
                "x": 2,
                "y": 2,
                "type": "CELL_TYPES.RECEIVER"
            },
            {
                "x": 3,
                "y": 2,
                "type": "CELL_TYPES.RECEIVER"
            },
            {
                "x": 4,
                "y": 2,
                "type": "CELL_TYPES.RECEIVER"
            },
            {
                "x": 2,
                "y": 4,
                "type": "CELL_TYPES.RECEIVER"
            },
            {
                "x": 3,
                "y": 4,
                "type": "CELL_TYPES.RECEIVER"
            },
            {
                "x": 4,
                "y": 4,
                "type": "CELL_TYPES.RECEIVER"
            },
            {
                "x": 1,
                "y": 1,
                "type": "CELL_TYPES.WALL"
            },
            {
                "x": 2,
                "y": 1,
                "type": "CELL_TYPES.WALL"
            },
            {
                "x": 3,
                "y": 1,
                "type": "CELL_TYPES.WALL"
            },
            {
                "x": 4,
                "y": 1,
                "type": "CELL_TYPES.WALL"
            },
            {
                "x": 5,
                "y": 1,
                "type": "CELL_TYPES.WALL"
            },
            {
                "x": 6,
                "y": 1,
                "type": "CELL_TYPES.WALL"
            },
            {
                "x": 1,
                "y": 3,
                "type": "CELL_TYPES.WALL"
            },
            {
                "x": 2,
                "y": 3,
                "type": "CELL_TYPES.WALL"
            },
            {
                "x": 3,
                "y": 3,
                "type": "CELL_TYPES.WALL"
            },
            {
                "x": 4,
                "y": 3,
                "type": "CELL_TYPES.WALL"
            },
            {
                "x": 5,
                "y": 3,
                "type": "CELL_TYPES.WALL"
            },
            {
                "x": 6,
                "y": 3,
                "type": "CELL_TYPES.WALL"
            },
            {
                "x": 0,
                "y": 4,
                "type": "CELL_TYPES.MIRROR_TRIANGLE",
                "rotation": 0,
                "locked": true,
                "fixedRotation": false
            },
            {
                "x": 6,
                "y": 2,
                "type": "CELL_TYPES.MIRROR_TRIANGLE",
                "rotation": 0,
                "locked": true,
                "fixedRotation": false
            }
        ],
        "emitters": [
            {
                "x": -1,
                "y": 0,
                "direction": "DIRECTIONS.RIGHT"
            }
        ],
        "inventory": {
            "mirror1": 2,
            "mirror2": 0
        }
    },
    {
        "id": 33,
        "name": "Level 33",
        "grid": {
            "width": 7,
            "height": 7
        },
        "items": [
            {
                "x": 2,
                "y": 6,
                "type": "CELL_TYPES.RECEIVER"
            },
            {
                "x": 5,
                "y": 5,
                "type": "CELL_TYPES.RECEIVER"
            },
            {
                "x": 6,
                "y": 2,
                "type": "CELL_TYPES.RECEIVER"
            },
            {
                "x": 6,
                "y": 4,
                "type": "CELL_TYPES.RECEIVER"
            },
            {
                "x": 2,
                "y": 2,
                "type": "CELL_TYPES.MIRROR_LINE",
                "rotation": 0,
                "locked": true,
                "fixedRotation": false
            },
            {
                "x": 4,
                "y": 4,
                "type": "CELL_TYPES.MIRROR_LINE",
                "rotation": 0,
                "locked": true,
                "fixedRotation": false
            }
        ],
        "emitters": [
            {
                "x": -1,
                "y": 2,
                "direction": "DIRECTIONS.RIGHT"
            },
            {
                "x": -1,
                "y": 4,
                "direction": "DIRECTIONS.RIGHT"
            },
            {
                "x": 2,
                "y": -1,
                "direction": "DIRECTIONS.DOWN"
            },
            {
                "x": 4,
                "y": -1,
                "direction": "DIRECTIONS.DOWN"
            }
        ],
        "inventory": {
            "mirror1": 1,
            "mirror2": 0
        }
    }
]